pysilenttask/__init__.py
pysilenttask/pysilenttask.py
pysilenttask-1.5.dist-info/LICENSE
pysilenttask-1.5.dist-info/METADATA
pysilenttask-1.5.dist-info/WHEEL
pysilenttask-1.5.dist-info/entry_points.txt
pysilenttask-1.5.dist-info/top_level.txt
pysilenttask-1.5.dist-info/RECORD
